elgas/__init__.py
elgas/application.py
elgas/client.py
elgas/connection.py
elgas/constants.py
elgas/exceptions.py
elgas/frames.py
elgas/integration.py
elgas/parser.py
elgas/security.py
elgas/state.py
elgas/transport.py
elgas/utils.py
elgas/parameters/__init__.py
elgas/parameters/analog_quantity.py
elgas/parameters/binary.py
elgas/parameters/compressibility.py
elgas/parameters/conversion_coefficient.py
elgas/parameters/counter.py
elgas/parameters/device_error.py
elgas/parameters/diagnostics.py
elgas/parameters/difference_counter.py
elgas/parameters/energy.py
elgas/parameters/enumerations.py
elgas/parameters/error_counter.py
elgas/parameters/error_standard_counter.py
elgas/parameters/factory.py
elgas/parameters/flow_rate.py
elgas/parameters/gas_composition.py
elgas/parameters/modem.py
elgas/parameters/setpoint.py
elgas/parameters/standard_counter.py
elgas/parameters/statistics.py
elgas/parameters/sum_of_alarms.py
elgas/parameters/system_parameters.py
elgas/parameters/tariff_counter.py
elgas/parameters/time_window.py
elgas/parameters/timer.py
elgas-24.1.0.dist-info/LICENSE
elgas-24.1.0.dist-info/METADATA
elgas-24.1.0.dist-info/WHEEL
elgas-24.1.0.dist-info/top_level.txt
elgas-24.1.0.dist-info/RECORD
