Metadata-Version: 2.1
Name: elgas
Version: 24.1.0
Summary: A Python library for the ELGAS protocol
Home-page: https://github.com/u9n/elgas
Author: Henrik Palmlund Wahlgren @ Palmlund Wahlgren Innovative Technology AB
Author-email: henrik.wahlgren@utilitarian.io
Maintainer: Henrik Palmlund Wahlgren @ Palmlund Wahlgren Innovative Technology AB
Maintainer-email: henrik.wahlgren@utilitarian.io
Project-URL: Bug Tracker, https://github.com/u9n/elgas/issues
Project-URL: Source Code, https://github.com/u9n/elgas
Keywords: AMR,Metering,smart meters,MDM,elgas,elcor,gas
Classifier: Intended Audience :: Developers
Classifier: Natural Language :: English
Classifier: Operating System :: OS Independent
Classifier: Programming Language :: Python :: 3
Classifier: Programming Language :: Python :: 3.6
Classifier: Programming Language :: Python :: 3.7
Classifier: Programming Language :: Python :: 3.8
Classifier: Programming Language :: Python :: 3.9
Classifier: Programming Language :: Python :: 3.10
Classifier: Programming Language :: Python :: 3.11
Classifier: Programming Language :: Python :: Implementation :: CPython
Classifier: Topic :: Software Development :: Libraries :: Python Modules
Requires-Python: ~=3.7
License-File: LICENSE
Requires-Dist: attrs >=21.4.0
Requires-Dist: cryptography ==42.0.5
Requires-Dist: marshmallow >=3.14.1
Requires-Dist: structlog >=21.5.0
Requires-Dist: pyserial ==3.5
Provides-Extra: dev
Requires-Dist: pre-commit ; extra == 'dev'
Requires-Dist: pytest ; extra == 'dev'
Provides-Extra: test
Requires-Dist: pytest ; extra == 'test'
